image_classification_package/BasicFinetunnedModels.json
image_classification_package/ImageDataLoader.json
image_classification_package/__init__.py
image_classification_package/basic_finetunned_models.py
image_classification_package/image_classification_model.py
image_classification_package/image_classification_task.py
image_classification_package/image_dataloader.json
image_classification_package/image_dataloader.py
image_classification_package-0.0.11.dist-info/METADATA
image_classification_package-0.0.11.dist-info/WHEEL
image_classification_package-0.0.11.dist-info/entry_points.txt
image_classification_package-0.0.11.dist-info/licenses/LICENSE
image_classification_package-0.0.11.dist-info/RECORD
