Metadata-Version: 2.1
Name: image_classification_package
Version: 0.0.11
Summary: This package includes all the necessary components to classify images using a pre-trained models.
Project-URL: Homepage, https://github.com/DashAISoftware/DashAI
Project-URL: Issues, https://github.com/DashAISoftware/DashAI/issues
Author-email: dashai <dashaisoftware@gmail.com>
License-File: LICENSE
Keywords: dashai,image classification,package,pytorch,torchvision
Classifier: License :: OSI Approved :: MIT License
Classifier: Operating System :: OS Independent
Classifier: Programming Language :: Python :: 3
Requires-Python: >=3.8
Requires-Dist: dashai
Requires-Dist: torchvision==0.14.0
